LICENSE.txt
MANIFEST.in
README.rst
setup.py
dist/manual.pdf
starfeeder/__init__.py
starfeeder/alembic.ini
starfeeder/balance.py
starfeeder/common_serial_testing.py
starfeeder/constants.py
starfeeder/gui.py
starfeeder/main.py
starfeeder/models.py
starfeeder/rfid.py
starfeeder/serial_controller.py
starfeeder/settings.py
starfeeder/task.py
starfeeder/test_mimic_balance.py
starfeeder/test_mimic_rfid_reader.py
starfeeder/version.py
starfeeder.egg-info/PKG-INFO
starfeeder.egg-info/SOURCES.txt
starfeeder.egg-info/dependency_links.txt
starfeeder.egg-info/entry_points.txt
starfeeder.egg-info/requires.txt
starfeeder.egg-info/top_level.txt
starfeeder/alembic/__init__.py
starfeeder/alembic/env.py
starfeeder/alembic/script.py.mako
starfeeder/alembic/versions/0001_start.py
starfeeder/alembic/versions/0002_0002.py
starfeeder/alembic/versions/0003_0003.py
starfeeder/alembic/versions/0004_perch_duration.py
starfeeder/alembic/versions/0005_mass_at_unlock.py
starfeeder/alembic/versions/__init__.py