Metadata-Version: 1.1
Name: starfeeder
Version: 0.3.4
Summary: Whisker Starfeeder (starling RFID/balance reader)
Home-page: http://www.whiskercontrol.com/
Author: Rudolf Cardinal
Author-email: rudolf@pobox.com
License: GNU General Public License v3 or later (GPLv3+)
Keywords: whisker rfid weigh balance starling
Platform: UNKNOWN
Classifier: Development Status :: 3 - Alpha
Classifier: Intended Audience :: Science/Research
Classifier: License :: OSI Approved :: GNU General Public License v3 or later (GPLv3+)
Classifier: Natural Language :: English
Classifier: Operating System :: OS Independent
Classifier: Programming Language :: Python :: 3
Classifier: Programming Language :: Python :: 3.5
Classifier: Programming Language :: Python :: 3 :: Only
Classifier: Topic :: System :: Hardware
Classifier: Topic :: System :: Networking
